simd_dna/__init__.py
simd_dna/classes.py
simd_dna/functions.py
simd_dna/register_svg.py
simd_dna/simulation.py
simd_dna/tm.py
simd_dna-1.0.1.dist-info/LICENSE.txt
simd_dna-1.0.1.dist-info/METADATA
simd_dna-1.0.1.dist-info/WHEEL
simd_dna-1.0.1.dist-info/top_level.txt
simd_dna-1.0.1.dist-info/RECORD
