Metadata-Version: 2.1
Name: simd-dna
Version: 1.0.1
Summary: UNKNOWN
Home-page: https://github.com/UC-Davis-molecular-computing/simd-dna
Author: David Doty and Aaron Ong
Author-email: aabong@ucdavis.edu
License: UNKNOWN
Platform: UNKNOWN
Requires-Python: >=3.8
License-File: LICENSE.txt
